{
    "type": "application",
    "source-directories": [
        ".",
        "../src",
        "../../elm-script/src"
    ],
    "elm-version": "0.19.1",
    "dependencies": {
        "direct": {
            "avh4/elm-color": "1.0.0",
            "elm/browser": "1.0.2",
            "elm/core": "1.0.4",
            "elm/html": "1.0.0",
            "elm/http": "2.0.0",
            "elm/json": "1.1.3",
            "elm/regex": "1.0.0",
            "elm/time": "1.0.0",
            "elm/url": "1.0.0",
            "elm-community/array-extra": "2.1.0",
            "elm-community/maybe-extra": "5.2.0",
            "elm-community/result-extra": "2.3.0",
            "elm-community/string-extra": "4.0.1",
            "elm-explorations/linear-algebra": "1.0.3",
            "elm-explorations/webgl": "1.1.1",
            "ianmackenzie/elm-1d-parameter": "1.0.1",
            "ianmackenzie/elm-3d-camera": "3.0.0",
            "ianmackenzie/elm-float-extra": "1.1.0",
            "ianmackenzie/elm-geometry": "3.5.0",
            "ianmackenzie/elm-geometry-linear-algebra-interop": "2.0.2",
            "ianmackenzie/elm-triangular-mesh": "1.0.4",
            "ianmackenzie/elm-units": "2.2.0",
            "ianmackenzie/elm-units-interval": "1.1.0",
            "mdgriffith/elm-ui": "1.1.5",
            "s6o/elm-recase": "1.0.1"
        },
        "indirect": {
            "elm/bytes": "1.0.8",
            "elm/file": "1.0.5",
            "elm/virtual-dom": "1.0.2",
            "ianmackenzie/elm-interval": "2.0.0"
        }
    },
    "test-dependencies": {
        "direct": {},
        "indirect": {}
    }
}
